pythia_ai/__init__.py
pythia_ai-0.0.1.dist-info/METADATA
pythia_ai-0.0.1.dist-info/WHEEL
pythia_ai-0.0.1.dist-info/RECORD
