Metadata-Version: 2.1
Name: pythia-ai
Version: 0.0.1
Summary: Your personal code oracle.
Author: The Epic
Author-email: theepic.dev.83@gmail.com
Requires-Python: >=3.11,<4.0
Classifier: Programming Language :: Python :: 3
Classifier: Programming Language :: Python :: 3.11
Classifier: Programming Language :: Python :: 3.12
Classifier: Programming Language :: Python :: 3.13
